pygremlinbox_c_uda_1_0/__init__.py
pygremlinbox_c_uda_1_0-1.4.0.dist-info/licenses/LICENCE
pygremlinbox_c_uda_1_0-1.4.0.dist-info/METADATA
pygremlinbox_c_uda_1_0-1.4.0.dist-info/WHEEL
pygremlinbox_c_uda_1_0-1.4.0.dist-info/top_level.txt
pygremlinbox_c_uda_1_0-1.4.0.dist-info/RECORD
